xiaoApple/__init__.py
xiaoApple/aliBackend.py
xiaoApple/copyfiles.py
xiaoApple/func.py
xiaoApple-0.0.10.dist-info/METADATA
xiaoApple-0.0.10.dist-info/WHEEL
xiaoApple-0.0.10.dist-info/top_level.txt
xiaoApple-0.0.10.dist-info/RECORD
