Metadata-Version: 2.1
Name: xiaoApple
Version: 0.0.10
Summary: 轻量级的阿里云盘同步脚本
Home-page: https://github.com/HengyueLi/xiaoApple
License: LICENSE.md
Requires-Python: >=3.10
Requires-Dist: tinysync >=0.0.16
Requires-Dist: aligo
